django_lighttpd_middleware/__init__.py
django_lighttpd_middleware-0.1.dist-info/LICENSE.md
django_lighttpd_middleware-0.1.dist-info/METADATA
django_lighttpd_middleware-0.1.dist-info/WHEEL
django_lighttpd_middleware-0.1.dist-info/top_level.txt
django_lighttpd_middleware-0.1.dist-info/RECORD
