Metadata-Version: 2.1
Name: django_lighttpd_middleware
Version: 0.1
Summary: Django Middleware for running a Django website under lighttpd
Home-page: https://github.com/bernd-wechner/django-lighttpd-middleware
Author: Bernd Wechner
Author-email: bwechner@yahoo.com
License: UNKNOWN
Project-URL: Bug Tracker, https://github.com/bernd-wechner/django-lighttpd-middleware/issues
Platform: UNKNOWN
Classifier: Programming Language :: Python :: 3
Classifier: License :: Freely Distributable
Classifier: Operating System :: OS Independent
Classifier: Development Status :: 4 - Beta
Classifier: Framework :: Django :: 3.2
Classifier: Intended Audience :: System Administrators
Classifier: Operating System :: OS Independent
Classifier: Topic :: Internet :: WWW/HTTP :: HTTP Servers
Requires-Python: >=3.6
License-File: LICENSE.md
